pyslise.cp310-win_amd64.pyd
pyslise-3.2.1.dist-info/METADATA
pyslise-3.2.1.dist-info/WHEEL
pyslise-3.2.1.dist-info/top_level.txt
pyslise-3.2.1.dist-info/RECORD
