Metadata-Version: 2.1
Name: pyslise
Version: 3.2.1
Summary: Python bindings for the C++ version of Matslise
Home-page: https://matslise.ugent.be/
Author: Toon Baeyens
Author-email: toon.baeyens@ugent.be
Requires-Dist: numpy
